tdmt/.gitignore
tdmt/Documentation.md
tdmt/README.md
tdmt/__init__.py
tdmt/add_key.py
tdmt/concat.py
tdmt/decorators.py
tdmt/diagnostics.py
tdmt/example_add_key.xlsx
tdmt/example_concat.xlsx
tdmt/example_filter_rows.xlsx
tdmt/example_format_dates.xlsx
tdmt/example_groupstats.xlsx
tdmt/example_hardcode_column.xlsx
tdmt/example_left_merge.xlsx
tdmt/example_map_and_rename1.xlsx
tdmt/example_map_and_rename2.xlsx
tdmt/example_multicolmap.xlsx
tdmt/example_skeleton1.xlsx
tdmt/example_skeleton2.xlsx
tdmt/example_transfer_key.xlsx
tdmt/example_unmerge.xlsx
tdmt/example_unstack.xlsx
tdmt/filter_rows.py
tdmt/format_dates.py
tdmt/groupstats.py
tdmt/hardcode_column.py
tdmt/left_merge.py
tdmt/map_and_rename.py
tdmt/multicolmap.py
tdmt/normal1.xlsx
tdmt/skeleton.py
tdmt/tdmt.py
tdmt/transfer_key.py
tdmt/unmerge.py
tdmt/unstack.py
tdmt/utils.py
tdmt/input/dummy_1.csv
tdmt/input/dummy_2.csv
tdmt/input/dummy_3.csv
tdmt/input/policy_dummy_1.csv
tdmt/input/policy_dummy_1_funny_dates.csv
tdmt/input/policy_dummy_1_funny_dates.xlsx
tdmt/input/policy_dummy_1_with_rows_to_filter.csv
tdmt/input/policy_dummy_2.csv
tdmt/input/transfer_key_table_1.csv
tdmt/input/transfer_key_table_2.csv
tdmt/input/unstack_test.csv
tdmt-1.0.1.dist-info/METADATA
tdmt-1.0.1.dist-info/WHEEL
tdmt-1.0.1.dist-info/entry_points.txt
tdmt-1.0.1.dist-info/RECORD
