Metadata-Version: 2.1
Name: tdmt
Version: 1.0.1
Summary: The Tabular Data Management Tool (tdmt) is a command line app to explore and transform data with a clear audit trail
Project-URL: Repository, https://gitlab.com/ml_usecases/tdmt
Project-URL: Documentation, https://gitlab.com/ml_usecases/tdmt/-/blob/main/Documentation.md?ref_type=heads
Author-email: ML User <uijnbh@gmail.com>
License-Expression: MIT
Classifier: License :: OSI Approved :: MIT License
Classifier: Operating System :: OS Independent
Classifier: Programming Language :: Python :: 3
Requires-Dist: et-xmlfile==1.1.0
Requires-Dist: exceptiongroup==1.1.3
Requires-Dist: iniconfig==2.0.0
Requires-Dist: numpy==1.25.2
Requires-Dist: openpyxl==3.0.9
Requires-Dist: packaging==23.1
Requires-Dist: pandas==1.4.2
Requires-Dist: pluggy==1.2.0
Requires-Dist: python-dateutil==2.8.2
Requires-Dist: pytz==2023.3
Requires-Dist: six==1.16.0
Requires-Dist: tomli==2.0.1
Requires-Dist: xlsxwriter==3.0.3
